bfet/__init__.py
bfet/__main__.py
bfet/cli.py
bfet/automatic_tests/__init__.py
bfet/automatic_tests/autotest.py
bfet/automatic_tests/create_tests.py
bfet/automatic_tests/django_tests.py
bfet/automatic_tests/settings.py
bfet/create_data/__init__.py
bfet/create_data/constants.py
bfet/create_data/create_data.py
bfet/testing_models/__init__.py
bfet/testing_models/django_model.py
bfet-0.1.11.dist-info/AUTHORS.rst
bfet-0.1.11.dist-info/LICENSE
bfet-0.1.11.dist-info/METADATA
bfet-0.1.11.dist-info/WHEEL
bfet-0.1.11.dist-info/entry_points.txt
bfet-0.1.11.dist-info/top_level.txt
bfet-0.1.11.dist-info/RECORD
