Metadata-Version: 2.1
Name: bfet
Version: 0.1.11
Summary: Better Faster Easier Testing. Create Django models quickly and easly, create different data types for testing cases or create default tests files
Home-page: https://github.com/lluc2397/bfet
Author: Lucas Montes
Author-email: lluc23@hotmail.com
License: MIT license
Keywords: bfet
Classifier: Development Status :: 2 - Pre-Alpha
Classifier: Intended Audience :: Developers
Classifier: License :: OSI Approved :: MIT License
Classifier: Natural Language :: English
Classifier: Programming Language :: Python :: 3
Classifier: Programming Language :: Python :: 3.6
Classifier: Programming Language :: Python :: 3.7
Classifier: Programming Language :: Python :: 3.8
Classifier: Programming Language :: Python :: 3.9
Classifier: Programming Language :: Python :: 3.10
Requires-Python: >=3.6
License-File: LICENSE
License-File: AUTHORS.rst
Requires-Dist: Jinja2
